[
    {
        "title": "I need help with my brakes",
        "text": "",
        "poster_id": "1",
        "image_link": "",
        "location_id": "1"
    },
    {
        "title": "I need help with my my plumbing",
        "text": "",
        "poster_id": "1",
        "image_link": "",
        "location_id": "1"
    },
    {
        "title": "I need help with my back pain",
        "text": "",
        "poster_id": "2",
        "image_link": "",
        "location_id": "1"
    },
    {
        "title": "I need help babysitting",
        "text": "",
        "poster_id": "2",
        "image_link": "",
        "location_id": "1"
    },
    {
        "title": "I need someone to do my lawn",
        "text": "",
        "poster_id": "3",
        "image_link": "",
        "location_id": "1"
    },
    {
        "title": "I need help with my AC",
        "text": "",
        "poster_id": "3",
        "image_link": "",
        "location_id": "1"
    },
    {
        "title": "I need help setting my band up on gig day!",
        "text": "",
        "poster_id": "4",
        "image_link": "",
        "location_id": "2"
    },
    {
        "title": "I need help tutoring my son",
        "text": "",
        "poster_id": "4",
        "image_link": "",
        "location_id": "2"
    },
    {
        "title": "I need help finding an affordable desktop PC",
        "text": "",
        "poster_id": "5",
        "image_link": "",
        "location_id": "3"
    },
    {
        "title": "I need help fixing my garage door",
        "text": "",
        "poster_id": "5",
        "image_link": "",
        "location_id": "3"
    },
    {
        "title": "I need help redoing my porch",
        "text": "",
        "poster_id": "6",
        "image_link": "",
        "location_id": "3"
    },
    {
        "title": "I need help with my plumbing",
        "text": "",
        "poster_id": "6",
        "image_link": "",
        "location_id": "3"
    },
    {
        "title": "I need a tutor for statistics",
        "text": "",
        "poster_id": "7",
        "image_link": "",
        "location_id": "4"
    },
    {
        "title": "I need help with my daughter's 7th grade science homework",
        "text": "",
        "poster_id": "7",
        "image_link": "",
        "location_id": "4"
    },
    {
        "title": "I need help finding a good mechanic",
        "text": "",
        "poster_id": "8",
        "image_link": "",
        "location_id": "4"
    },
    {
        "title": "I need a personal chef for my birthday",
        "text": "",
        "poster_id": "8",
        "image_link": "",
        "location_id": "4"
    },
    {
        "title": "I need a Javascript tutor?",
        "text": "",
        "poster_id": "9",
        "image_link": "",
        "location_id": "4"
    },
    {
        "title": "I need to change my car's oil",
        "text": "",
        "poster_id": "9",
        "image_link": "",
        "location_id": "4"
    },
    {
        "title": "I need a hug",
        "text": "",
        "poster_id": "10",
        "image_link": "",
        "location_id": "5"
    },
    {
        "title": "I need help finding my dog",
        "text": "",
        "poster_id": "10",
        "image_link": "",
        "location_id": "5"
    },
    {
        "title": "I need to paint my house",
        "text": "",
        "poster_id": "11",
        "image_link": "",
        "location_id": "5"
    },
    {
        "title": "I need to find a babysitter!",
        "text": "",
        "poster_id": "11",
        "image_link": "",
        "location_id": "5"
    },
    {
        "title": "I need someone to do my hair please?",
        "text": "",
        "poster_id": "12",
        "image_link": "",
        "location_id": "5"
    },
    {
        "title": "I need someone to make dinner for my grandmother",
        "text": "",
        "poster_id": "12",
        "image_link": "",
        "location_id": "5"
    },
    {
        "title": "I need help stimulating my dog's anal glands",
        "text": "",
        "poster_id": "13",
        "image_link": "",
        "location_id": "6"
    },
    {
        "title": "Can someone help me train my dog???",
        "text": "",
        "poster_id": "13",
        "image_link": "",
        "location_id": "6"
    },
    {
        "title": "I need a professional massage",
        "text": "",
        "poster_id": "14",
        "image_link": "",
        "location_id": "6"
    },
    {
        "title": "Is anyone a physical trainer? WILL PAY!",
        "text": "",
        "poster_id": "14",
        "image_link": "",
        "location_id": "6"
    },
    {
        "title": "My daughter needs help with math!",
        "text": "",
        "poster_id": "15",
        "image_link": "",
        "location_id": "6"
    },
    {
        "title": "I need help with",
        "text": "",
        "poster_id": "15",
        "image_link": "",
        "location_id": "6"
    },
    {
        "title": "I need help with",
        "text": "",
        "poster_id": "16",
        "image_link": "",
        "location_id": "1"
    },
    {
        "title": "I need help with",
        "text": "",
        "poster_id": "16",
        "image_link": "",
        "location_id": "2"
    },
    {
        "title": "I need help with",
        "text": "",
        "poster_id": "17",
        "image_link": "",
        "location_id": "3"
    },
    {
        "title": "I need help with",
        "text": "",
        "poster_id": "17",
        "image_link": "",
        "location_id": "4"
    },
    {
        "title": "I need help with",
        "text": "",
        "poster_id": "18",
        "image_link": "",
        "location_id": "5"
    },
    {
        "title": "I need help with",
        "text": "",
        "poster_id": "18",
        "image_link": "",
        "location_id": "6"
    }
]